CHANGES.txt
COPYRIGHT.txt
LICENSE.txt
MANIFEST.in
README.rst
setup.cfg
setup.py
pyramid_maintenance/__init__.py
pyramid_maintenance/tests.py
pyramid_maintenance.egg-info/PKG-INFO
pyramid_maintenance.egg-info/SOURCES.txt
pyramid_maintenance.egg-info/dependency_links.txt
pyramid_maintenance.egg-info/entry_points.txt
pyramid_maintenance.egg-info/not-zip-safe
pyramid_maintenance.egg-info/requires.txt
pyramid_maintenance.egg-info/top_level.txt
pyramid_maintenance/tests/templates/maintenance.mako
pyramid_maintenance/tests/templates/something.mako