Metadata-Version: 1.1
Name: pyramid-maintenance
Version: 0.1
Summary: pyramid_maintenance
Home-page: UNKNOWN
Author: Benoît Pineau
Author-email: beny@sickless.net
License: UNKNOWN
Keywords: web pyramid pylons
Platform: UNKNOWN
Classifier: Programming Language :: Python
Classifier: Framework :: Pyramid
Classifier: Topic :: Internet :: WWW/HTTP
Classifier: Topic :: Internet :: WWW/HTTP :: WSGI :: Application
